[

  {
    "title": "風車",
    "x": 540,
    "y": 1978,
    "desc": "風車の音",
    "photo": "photo/husha.jpg",
    "playlist": [
      {
        "name": "高野:風車下",
        "file": "audio/高野20251012_102905風車下.mp3"
      },
      {
        "name": "高野:風車下水路",
        "file": "audio/高野20251012_103316風車下水路.mp3"
      },
      {
        "name": "高野:風車下モーター",
        "file": "audio/高野20251012_103450風車下モーター？.mp3"
      },
      {
        "name": "高野:風車階段",
        "file": "audio/高野20251012_103601風車階段.mp3"
      }
    ]
  }
]
